<?xml version="1.0" encoding="UTF-8" ?>
<!DOCTYPE mapper PUBLIC "-//mybatis.org//DTD Mapper 3.0//EN" "http://mybatis.org/dtd/mybatis-3-mapper.dtd" >
<mapper
	namespace="com.service.manager.user.persistence.mapper.ProductSubCategoryMapper">
	<resultMap id="BaseResultMap"
		type="com.service.manager.user.persistence.ProductSubCategory">
		<!-- WARNING - @mbggenerated This element is automatically generated by 
			MyBatis Generator, do not modify. This element was generated on Sun Feb 12 
			00:05:38 IST 2017. -->
		<id column="sub_category_id" property="subCategoryId" jdbcType="INTEGER" />
		<result column="sub_category_name" property="subCategoryName"
			jdbcType="VARCHAR" />
	</resultMap>
	<sql id="Example_Where_Clause">
		<!-- WARNING - @mbggenerated This element is automatically generated by 
			MyBatis Generator, do not modify. This element was generated on Sun Feb 12 
			00:05:38 IST 2017. -->
		<where>
			<foreach collection="oredCriteria" item="criteria" separator="or">
				<if test="criteria.valid">
					<trim prefix="(" suffix=")" prefixOverrides="and">
						<foreach collection="criteria.criteria" item="criterion">
							<choose>
								<when test="criterion.noValue">
									and ${criterion.condition}
								</when>
								<when test="criterion.singleValue">
									and ${criterion.condition} #{criterion.value}
								</when>
								<when test="criterion.betweenValue">
									and ${criterion.condition} #{criterion.value} and
									#{criterion.secondValue}
								</when>
								<when test="criterion.listValue">
									and ${criterion.condition}
									<foreach collection="criterion.value" item="listItem"
										open="(" close=")" separator=",">
										#{listItem}
									</foreach>
								</when>
							</choose>
						</foreach>
					</trim>
				</if>
			</foreach>
		</where>
	</sql>
	<sql id="Update_By_Example_Where_Clause">
		<!-- WARNING - @mbggenerated This element is automatically generated by 
			MyBatis Generator, do not modify. This element was generated on Sun Feb 12 
			00:05:38 IST 2017. -->
		<where>
			<foreach collection="example.oredCriteria" item="criteria"
				separator="or">
				<if test="criteria.valid">
					<trim prefix="(" suffix=")" prefixOverrides="and">
						<foreach collection="criteria.criteria" item="criterion">
							<choose>
								<when test="criterion.noValue">
									and ${criterion.condition}
								</when>
								<when test="criterion.singleValue">
									and ${criterion.condition} #{criterion.value}
								</when>
								<when test="criterion.betweenValue">
									and ${criterion.condition} #{criterion.value} and
									#{criterion.secondValue}
								</when>
								<when test="criterion.listValue">
									and ${criterion.condition}
									<foreach collection="criterion.value" item="listItem"
										open="(" close=")" separator=",">
										#{listItem}
									</foreach>
								</when>
							</choose>
						</foreach>
					</trim>
				</if>
			</foreach>
		</where>
	</sql>
	<sql id="Base_Column_List">
		<!-- WARNING - @mbggenerated This element is automatically generated by 
			MyBatis Generator, do not modify. This element was generated on Sun Feb 12 
			00:05:38 IST 2017. -->
		sub_category_id, sub_category_name
	</sql>
	<select id="selectByExample" resultMap="BaseResultMap"
		parameterType="com.service.manager.user.persistence.ProductSubCategoryExample">
		<!-- WARNING - @mbggenerated This element is automatically generated by 
			MyBatis Generator, do not modify. This element was generated on Sun Feb 12 
			00:05:38 IST 2017. -->
		select
		<if test="distinct">
			distinct
		</if>
		<include refid="Base_Column_List" />
		from product_sub_category
		<if test="_parameter != null">
			<include refid="Example_Where_Clause" />
		</if>
		<if test="orderByClause != null">
			order by ${orderByClause}
		</if>
	</select>
	<select id="selectByPrimaryKey" resultMap="BaseResultMap"
		parameterType="java.lang.Integer">
		<!-- WARNING - @mbggenerated This element is automatically generated by 
			MyBatis Generator, do not modify. This element was generated on Sun Feb 12 
			00:05:38 IST 2017. -->
		select
		<include refid="Base_Column_List" />
		from product_sub_category
		where sub_category_id = #{subCategoryId,jdbcType=INTEGER}
	</select>
	<delete id="deleteByPrimaryKey" parameterType="java.lang.Integer">
		<!-- WARNING - @mbggenerated This element is automatically generated by 
			MyBatis Generator, do not modify. This element was generated on Sun Feb 12 
			00:05:38 IST 2017. -->
		delete from product_sub_category
		where sub_category_id = #{subCategoryId,jdbcType=INTEGER}
	</delete>
	<delete id="deleteByExample"
		parameterType="com.service.manager.user.persistence.ProductSubCategoryExample">
		<!-- WARNING - @mbggenerated This element is automatically generated by 
			MyBatis Generator, do not modify. This element was generated on Sun Feb 12 
			00:05:38 IST 2017. -->
		delete from product_sub_category
		<if test="_parameter != null">
			<include refid="Example_Where_Clause" />
		</if>
	</delete>
	<insert id="insert"
		parameterType="com.service.manager.user.persistence.ProductSubCategory">
		<!-- WARNING - @mbggenerated This element is automatically generated by 
			MyBatis Generator, do not modify. This element was generated on Sun Feb 12 
			00:05:38 IST 2017. -->
		insert into product_sub_category (sub_category_id, sub_category_name)
		values (#{subCategoryId,jdbcType=INTEGER},
		#{subCategoryName,jdbcType=VARCHAR})
	</insert>
	<insert id="insertSelective"
		parameterType="com.service.manager.user.persistence.ProductSubCategory">
		<!-- WARNING - @mbggenerated This element is automatically generated by 
			MyBatis Generator, do not modify. This element was generated on Sun Feb 12 
			00:05:38 IST 2017. -->
		insert into product_sub_category
		<trim prefix="(" suffix=")" suffixOverrides=",">
			<if test="subCategoryId != null">
				sub_category_id,
			</if>
			<if test="subCategoryName != null">
				sub_category_name,
			</if>
		</trim>
		<trim prefix="values (" suffix=")" suffixOverrides=",">
			<if test="subCategoryId != null">
				#{subCategoryId,jdbcType=INTEGER},
			</if>
			<if test="subCategoryName != null">
				#{subCategoryName,jdbcType=VARCHAR},
			</if>
		</trim>
	</insert>
	<select id="countByExample"
		parameterType="com.service.manager.user.persistence.ProductSubCategoryExample"
		resultType="java.lang.Integer">
		<!-- WARNING - @mbggenerated This element is automatically generated by 
			MyBatis Generator, do not modify. This element was generated on Sun Feb 12 
			00:05:38 IST 2017. -->
		select count(*) from product_sub_category
		<if test="_parameter != null">
			<include refid="Example_Where_Clause" />
		</if>
	</select>
	<update id="updateByExampleSelective" parameterType="map">
		<!-- WARNING - @mbggenerated This element is automatically generated by 
			MyBatis Generator, do not modify. This element was generated on Sun Feb 12 
			00:05:38 IST 2017. -->
		update product_sub_category
		<set>
			<if test="record.subCategoryId != null">
				sub_category_id = #{record.subCategoryId,jdbcType=INTEGER},
			</if>
			<if test="record.subCategoryName != null">
				sub_category_name = #{record.subCategoryName,jdbcType=VARCHAR},
			</if>
		</set>
		<if test="_parameter != null">
			<include refid="Update_By_Example_Where_Clause" />
		</if>
	</update>
	<update id="updateByExample" parameterType="map">
		<!-- WARNING - @mbggenerated This element is automatically generated by 
			MyBatis Generator, do not modify. This element was generated on Sun Feb 12 
			00:05:38 IST 2017. -->
		update product_sub_category
		set sub_category_id = #{record.subCategoryId,jdbcType=INTEGER},
		sub_category_name = #{record.subCategoryName,jdbcType=VARCHAR}
		<if test="_parameter != null">
			<include refid="Update_By_Example_Where_Clause" />
		</if>
	</update>
	<update id="updateByPrimaryKeySelective"
		parameterType="com.service.manager.user.persistence.ProductSubCategory">
		<!-- WARNING - @mbggenerated This element is automatically generated by 
			MyBatis Generator, do not modify. This element was generated on Sun Feb 12 
			00:05:38 IST 2017. -->
		update product_sub_category
		<set>
			<if test="subCategoryName != null">
				sub_category_name = #{subCategoryName,jdbcType=VARCHAR},
			</if>
		</set>
		where sub_category_id = #{subCategoryId,jdbcType=INTEGER}
	</update>
	<update id="updateByPrimaryKey"
		parameterType="com.service.manager.user.persistence.ProductSubCategory">
		<!-- WARNING - @mbggenerated This element is automatically generated by 
			MyBatis Generator, do not modify. This element was generated on Sun Feb 12 
			00:05:38 IST 2017. -->
		update product_sub_category
		set sub_category_name = #{subCategoryName,jdbcType=VARCHAR}
		where sub_category_id = #{subCategoryId,jdbcType=INTEGER}
	</update>

	<select id="getAllSubCategories" resultMap="BaseResultMap">
		select * from
		product_sub_category
	</select>
	
<!-- 	<select id="getAllSubCategories" resultMap="BaseResultMap">
		SELECT
			sub_cat.`sub_category_id`,
			sub_cat.`sub_category_name`
		FROM
		product_sub_category sub_cat
	</select> -->
		
	<select id="getCategoriesByCategoryId" resultMap="BaseResultMap">

		SELECT
			sub_cat.`sub_category_id`,
			sub_cat.`sub_category_name`
		FROM
		product_sub_category sub_cat
		LEFT OUTER JOIN
		category_sub_category cat_sub_cat
		ON sub_cat.`sub_category_id` = cat_sub_cat.`sub_category_id`
		<if test="categoryId != null">
			WHERE cat_sub_cat.`category_id` = #{categoryId}
		</if>
	</select>
</mapper>